Workbook

Sheet Dataset
A1: ID | B1: Category | C1: Prompt | D1: Response | E1: Input Tokens (est.) | F1: Output Tokens (est.) | G1: Total Tokens (est.) | H1: Tier | I1: Primary Driver Note
A2: 1 | B2: Quick Factual Lookup | C2: What's the capital of Japan? | D2: The capital of Japan is Tokyo. | E2: =ROUND(LEN(C2)/4,0) -> 7 | F2: =ROUND(LEN(D2)/4,0) -> 8 | G2: =E2+F2 -> 15 | H2: =IF(G2<100,"Low",IF(G2<250,"Medium","High")) -> Low | I2: single fact, no elaboration requested
A3: 2 | B3: Quick Factual Lookup | C3: What year did World War II end? | D3: World War II ended in 1945. | E3: =ROUND(LEN(C3)/4,0) -> 8 | F3: =ROUND(LEN(D3)/4,0) -> 7 | G3: =E3+F3 -> 15 | H3: =IF(G3<100,"Low",IF(G3<250,"Medium","High")) -> Low | I3: single fact
A4: 3 | B4: Quick Factual Lookup | C4: How many continents are there? | D4: There are seven continents: Africa, Antarctica, Asia, Australia, Europe, North America, and South America. | E4: =ROUND(LEN(C4)/4,0) -> 8 | F4: =ROUND(LEN(D4)/4,0) -> 27 | G4: =E4+F4 -> 35 | H4: =IF(G4<100,"Low",IF(G4<250,"Medium","High")) -> Low | I4: single fact, enumerated list
A5: 4 | B5: Quick Factual Lookup | C5: What is the boiling point of water in Celsius at sea level? | D5: Water boils at 100 degrees Celsius (212 degrees Fahrenheit) at standard sea-level atmospheric pressure. | E5: =ROUND(LEN(C5)/4,0) -> 15 | F5: =ROUND(LEN(D5)/4,0) -> 26 | G5: =E5+F5 -> 41 | H5: =IF(G5<100,"Low",IF(G5<250,"Medium","High")) -> Low | I5: single fact with unit conversion
A6: 5 | B6: Quick Factual Lookup | C6: Who wrote Romeo and Juliet and when? | D6: Romeo and Juliet was written by William Shakespeare, believed to have been composed between 1591 and 1595. | E6: =ROUND(LEN(C6)/4,0) -> 9 | F6: =ROUND(LEN(D6)/4,0) -> 27 | G6: =E6+F6 -> 36 | H6: =IF(G6<100,"Low",IF(G6<250,"Medium","High")) -> Low | I6: single fact with date range
A7: 6 | B7: Quick Factual Lookup | C7: What's the chemical symbol for gold? | D7: The chemical symbol for gold is Au, from the Latin word aurum. | E7: =ROUND(LEN(C7)/4,0) -> 9 | F7: =ROUND(LEN(D7)/4,0) -> 16 | G7: =E7+F7 -> 25 | H7: =IF(G7<100,"Low",IF(G7<250,"Medium","High")) -> Low | I7: single fact with etymology
A8: 7 | B8: Definitions & Short Explanations | C8: Explain what an API is in one sentence. | D8: An API (Application Programming Interface) is a set of rules that lets one piece of software request services or data from another. | E8: =ROUND(LEN(C8)/4,0) -> 10 | F8: =ROUND(LEN(D8)/4,0) -> 33 | G8: =E8+F8 -> 43 | H8: =IF(G8<100,"Low",IF(G8<250,"Medium","High")) -> Low | I8: explicitly constrained to one sentence
A9: 8 | B9: Definitions & Short Explanations | C9: Define machine learning in simple terms. | D9: Machine learning is a branch of AI where computer systems improve at a task by learning patterns from data, rather than following rules written explicitly by a programmer. | E9: =ROUND(LEN(C9)/4,0) -> 10 | F9: =ROUND(LEN(D9)/4,0) -> 43 | G9: =E9+F9 -> 53 | H9: =IF(G9<100,"Low",IF(G9<250,"Medium","High")) -> Low | I9: no length constraint given, moderate elaboration
A10: 9 | B10: Definitions & Short Explanations | C10: What is compound interest? Explain with a short example. | D10: Compound interest is interest calculated on both the original principal and the interest already earned. For example, $1,000 at 5% annual interest becomes $1,050 after year one, and $1,102.50 after year two, because the second year's interest is calculated on $1,050, not the original $1,000. | E10: =ROUND(LEN(C10)/4,0) -> 14 | F10: =ROUND(LEN(D10)/4,0) -> 73 | G10: =E10+F10 -> 87 | H10: =IF(G10<100,"Low",IF(G10<250,"Medium","High")) -> Low | I10: example requested, adds a worked calculation
A11: 10 | B11: Definitions & Short Explanations | C11: Explain the difference between HTTP and HTTPS. | D11: HTTP (Hypertext Transfer Protocol) sends data between a browser and a server in plain text. HTTPS adds a layer of encryption (TLS/SSL) on top of HTTP, so data in transit is scrambled and can't easily be read or tampered with by a third party. The 'S' stands for secure, and HTTPS is now the standard for any site handling passwords, payments, or personal data. | E11: =ROUND(LEN(C11)/4,0) -> 12 | F11: =ROUND(LEN(D11)/4,0) -> 90 | G11: =E11+F11 -> 102 | H11: =IF(G11<100,"Low",IF(G11<250,"Medium","High")) -> Medium | I11: comparison of two concepts, three distinct points
A12: 11 | B12: Definitions & Short Explanations | C12: What is a firewall and how does it work? | D12: A firewall is a security system that monitors and filters network traffic based on a defined set of rules. It sits between a trusted internal network and an untrusted external one (like the internet), inspecting incoming and outgoing packets and blocking or allowing them based on criteria like source IP, destination port, or protocol. Firewalls can be hardware devices, software running on a server, or built into a router, and they're typically the first line of defense against unauthorized access. | E12: =ROUND(LEN(C12)/4,0) -> 10 | F12: =ROUND(LEN(D12)/4,0) -> 126 | G12: =E12+F12 -> 136 | H12: =IF(G12<100,"Low",IF(G12<250,"Medium","High")) -> Medium | I12: mechanism explanation, multiple implementation types covered
A13: 12 | B13: Definitions & Short Explanations | C13: Define supply and demand with a simple example. | D13: Supply and demand describes how the price of a good is determined by how much of it is available (supply) versus how much people want it (demand). For example, if a new phone model launches with limited stock but high demand, the price tends to rise. If a farmer has a bumper crop of tomatoes and supply outpaces demand, prices tend to fall until the surplus clears. | E13: =ROUND(LEN(C13)/4,0) -> 12 | F13: =ROUND(LEN(D13)/4,0) -> 92 | G13: =E13+F13 -> 104 | H13: =IF(G13<100,"Low",IF(G13<250,"Medium","High")) -> Medium | I13: example requested, two-sided illustration
... A61: 60 | B61: Multi-Step Reasoning | C61: Work through this optimization problem step by step: a rectangular garden must have an area of 200 square meters, and the owner wants to minimize the amount of fencing used. Find the dimensions that minimize the perimeter. | D61: Step 1 — Set up variables. Let the length be L and width be W. The area constraint gives us L * W = 200. Step 2 — Write the objective function. Perimeter P = 2L + 2W. We want to minimize this subject to the area constraint. Step 3 — Reduce to one variable. From the constraint, W = 200/L. Substitute into the perimeter formula: P = 2L + 2(200/L) = 2L + 400/L. Step 4 — Take the derivative. dP/dL = 2 - 400/L^2. Step 5 — Set the derivative to zero to find critical points. 2 - 400/L^2 = 0, so 400/L^2 = 2, which gives L^2 = 200, so L = sqrt(200) ≈ 14.14 meters. Step 6 — Find W using the constraint. W = 200/L = 200/14.14 ≈ 14.14 meters. Step 7 — Verify it's a minimum. The second derivative, d^2P/dL^2 = 800/L^3, is positive for L > 0, confirming this critical point is indeed a minimum, not a maximum. Conclusion: The perimeter is minimized when the garden is a square, approximately 14.14 meters by 14.14 meters, giving a minimum perimeter of about 56.57 meters. This makes intuitive sense — for a fixed area, a square always minimizes perimeter among rectangles. | E61: =ROUND(LEN(C61)/4,0) -> 56 | F61: =ROUND(LEN(D61)/4,0) -> 268 | G61: =E61+F61 -> 324 | H61: =IF(G61<100,"Low",IF(G61<250,"Medium","High")) -> High | I61: calculus-based optimization requiring derivative steps and a verification check

Sheet Category Summary
A1: Category | B1: # Prompts | C1: Avg Input Tokens | D1: Avg Output Tokens | E1: Avg Total Tokens | F1: Output Share % | G1: Tier
A2: Summarization | B2: =COUNTIF(Dataset!B:B,A2) -> 6 | C2: =ROUND(AVERAGEIF(Dataset!B:B,A2,Dataset!E:E),1) -> 284.7 | D2: =ROUND(AVERAGEIF(Dataset!B:B,A2,Dataset!F:F),1) -> 108.5 | E2: =ROUND(C2+D2,1) -> 393.2 | F2: =ROUND(D2/E2*100,1) -> 27.6 | G2: =IF(E2<100,"Low",IF(E2<250,"Medium","High")) -> High
A3: Multi-Step Reasoning | B3: =COUNTIF(Dataset!B:B,A3) -> 6 | C3: =ROUND(AVERAGEIF(Dataset!B:B,A3,Dataset!E:E),1) -> 50.3 | D3: =ROUND(AVERAGEIF(Dataset!B:B,A3,Dataset!F:F),1) -> 298.5 | E3: =ROUND(C3+D3,1) -> 348.8 | F3: =ROUND(D3/E3*100,1) -> 85.6 | G3: =IF(E3<100,"Low",IF(E3<250,"Medium","High")) -> High
A4: Document/Data Analysis | B4: =COUNTIF(Dataset!B:B,A4) -> 6 | C4: =ROUND(AVERAGEIF(Dataset!B:B,A4,Dataset!E:E),1) -> 83.3 | D4: =ROUND(AVERAGEIF(Dataset!B:B,A4,Dataset!F:F),1) -> 215 | E4: =ROUND(C4+D4,1) -> 298.3 | F4: =ROUND(D4/E4*100,1) -> 72.1 | G4: =IF(E4<100,"Low",IF(E4<250,"Medium","High")) -> High
A5: Long-Form Creative Writing | B5: =COUNTIF(Dataset!B:B,A5) -> 6 | C5: =ROUND(AVERAGEIF(Dataset!B:B,A5,Dataset!E:E),1) -> 19.2 | D5: =ROUND(AVERAGEIF(Dataset!B:B,A5,Dataset!F:F),1) -> 237.7 | E5: =ROUND(C5+D5,1) -> 256.9 | F5: =ROUND(D5/E5*100,1) -> 92.5 | G5: =IF(E5<100,"Low",IF(E5<250,"Medium","High")) -> High
A6: Code Generation | B6: =COUNTIF(Dataset!B:B,A6) -> 6 | C6: =ROUND(AVERAGEIF(Dataset!B:B,A6,Dataset!E:E),1) -> 22.3 | D6: =ROUND(AVERAGEIF(Dataset!B:B,A6,Dataset!F:F),1) -> 231.3 | E6: =ROUND(C6+D6,1) -> 253.6 | F6: =ROUND(D6/E6*100,1) -> 91.2 | G6: =IF(E6<100,"Low",IF(E6<250,"Medium","High")) -> High
A7: Code Debugging & Explanation | B7: =COUNTIF(Dataset!B:B,A7) -> 6 | C7: =ROUND(AVERAGEIF(Dataset!B:B,A7,Dataset!E:E),1) -> 41.5 | D7: =ROUND(AVERAGEIF(Dataset!B:B,A7,Dataset!F:F),1) -> 176.3 | E7: =ROUND(C7+D7,1) -> 217.8 | F7: =ROUND(D7/E7*100,1) -> 80.9 | G7: =IF(E7<100,"Low",IF(E7<250,"Medium","High")) -> Medium
A8: Translation | B8: =COUNTIF(Dataset!B:B,A8) -> 6 | C8: =ROUND(AVERAGEIF(Dataset!B:B,A8,Dataset!E:E),1) -> 71.3 | D8: =ROUND(AVERAGEIF(Dataset!B:B,A8,Dataset!F:F),1) -> 54.3 | E8: =ROUND(C8+D8,1) -> 125.6 | F8: =ROUND(D8/E8*100,1) -> 43.2 | G8: =IF(E8<100,"Low",IF(E8<250,"Medium","High")) -> Medium
A9: Definitions & Short Explanations | B9: =COUNTIF(Dataset!B:B,A9) -> 6 | C9: =ROUND(AVERAGEIF(Dataset!B:B,A9,Dataset!E:E),1) -> 11.3 | D9: =ROUND(AVERAGEIF(Dataset!B:B,A9,Dataset!F:F),1) -> 76.2 | E9: =ROUND(C9+D9,1) -> 87.5 | F9: =ROUND(D9/E9*100,1) -> 87.1 | G9: =IF(E9<100,"Low",IF(E9<250,"Medium","High")) -> Low
A10: Casual Conversation | B10: =COUNTIF(Dataset!B:B,A10) -> 6 | C10: =ROUND(AVERAGEIF(Dataset!B:B,A10,Dataset!E:E),1) -> 8.2 | D10: =ROUND(AVERAGEIF(Dataset!B:B,A10,Dataset!F:F),1) -> 42.2 | E10: =ROUND(C10+D10,1) -> 50.4 | F10: =ROUND(D10/E10*100,1) -> 83.7 | G10: =IF(E10<100,"Low",IF(E10<250,"Medium","High")) -> Low
A11: Quick Factual Lookup | B11: =COUNTIF(Dataset!B:B,A11) -> 6 | C11: =ROUND(AVERAGEIF(Dataset!B:B,A11,Dataset!E:E),1) -> 9.3 | D11: =ROUND(AVERAGEIF(Dataset!B:B,A11,Dataset!F:F),1) -> 18.5 | E11: =ROUND(C11+D11,1) -> 27.8 | F11: =ROUND(D11/E11*100,1) -> 66.5 | G11: =IF(E11<100,"Low",IF(E11<250,"Medium","High")) -> Low
A13: Overall (all categories) | B13: =SUM(B2:B11) -> 60 | C13: =ROUND(AVERAGE(C2:C11),1) -> 60.1 | D13: =ROUND(AVERAGE(D2:D11),1) -> 145.9 | E13: =ROUND(AVERAGE(E2:E11),1) -> 206
A14: Total tokens, whole dataset | B14: =SUM(Dataset!G2:G61) -> 12360

Sheet Methodology
A1: Taxonomy of AI Prompts — Token Usage by Category
A3: Purpose
A4: Categorize prompt/task types by total token usage (input + output) to identify where cost is concentrated, and what specifically drives high usage within each category, in order to inform cost-optimization decisions.
A6: Dataset
A7: 60 synthetic prompt/response pairs across 10 task categories, built with deliberate length variation within each category (short/medium/long variants) so both cross-category and within-category drivers are visible. This is a starter dataset for methodology validation — swap in real prompts and responses from your own logs, and the token estimates and tiers will recalculate automatically.
A9: Token estimation method
A10: Tokens are estimated as text length in characters / 4, rounded — a standard, widely-used approximation for English text and code (roughly accurate to +/-10-15%). This environment did not have API/network access to compute exact tokenizer counts, so treat these as directional estimates, sufficient for ranking categories relative to each other. For exact counts against your real prompts, see 'Getting exact token counts' below.
A12: Tier definitions
A13: Low: under 100 estimated total tokens | Medium: 100-249 tokens | High: 250+ tokens. Thresholds were chosen from the observed spread in this dataset — revisit them once real usage data is in, since your actual distribution may shift the natural breakpoints.
A15: Getting exact token counts (recommended next step)
A16: 1) Anthropic Console / Workbench — paste a prompt and it shows exact token counts before you run it.
A17: 2) API responses — every Claude API call returns usage.input_tokens and usage.output_tokens on the response object; logging these for real traffic is the most accurate long-term approach.
... A19: 4) Local tokenizers — libraries such as tiktoken (OpenAI) approximate well for rough estimation when no API access is available, though they are not identical to Claude's tokenizer.
